musicnotes_rm/MusicnotesRM.py
musicnotes_rm/__init__.py
unwatermark_musicnotes-1.0.1.dist-info/LICENSE
unwatermark_musicnotes-1.0.1.dist-info/METADATA
unwatermark_musicnotes-1.0.1.dist-info/WHEEL
unwatermark_musicnotes-1.0.1.dist-info/entry_points.txt
unwatermark_musicnotes-1.0.1.dist-info/top_level.txt
unwatermark_musicnotes-1.0.1.dist-info/RECORD
