Metadata-Version: 2.1
Name: unwatermark-musicnotes
Version: 1.0.1
Summary: A Musicnotes PDF watermark remover
Home-page: https://github.com/jasyip/unwatermark-musicnotes
Author: Jason Yip
Author-email: jasonyip1234567@gmail.com
License: MIT
Platform: UNKNOWN
Classifier: Programming Language :: Python :: 3
Requires-Python: >=3
License-File: LICENSE
Requires-Dist: pymupdf
